task3/ram.sv
module ram (
    input logic clk,     
    input logic wr_en,
    input logic rd_en,
    input logic [8:0] wr_addr,    
    input logic [8:0] rd_addr,
    input logic [8:0] din,
    output logic [8:0] dout     
); 

    logic [8:0] ram_array [511:0];

    always_ff @(posedge clk) begin
        if (wr_en)
            ram_array[wr_addr] <= din;
        if (rd_en)
            dout <= ram_array[rd_addr];
    end
endmodule

task3/counter.sv
module counter(
    input  logic clk,     //clock
    input  logic rst,     //reset
    input  logic en,      //counter enable
    input  logic [8:0] incr,    //counter start?
    output logic [8:0] count    //count output
);

always_ff @ (posedge clk)
    if (rst)    count <= incr;
    else if(en)      count <= count + incr;

endmodule

task3/sigdelay.sv
module sigdelay(
    input logic rst,
    input logic wr,
    input logic rd,
    input logic clk,
    input logic [8:0] offset,
    input logic [8:0] mic_signal,
    output logic [8:0] delayed_signal 
);

    logic [8:0] addr1;

    counter counter(
        .clk(clk),
        .rst(rst),
        .en(wr),
        .incr(mic_signal),
        .count(addr1)
    );

    ram ram(
        .clk(clk),
        .wr_en(wr),
        .rd_en(rd),
        .wr_addr(addr1),
        .rd_addr(addr1 + offset),
        .din(mic_signal),
        .dout(delayed_signal)
    );

endmodule

task3/sigdelay.vcd
$version Generated by VerilatedVcd $end
$date Mon Nov  6 03:14:56 2023 $end
$timescale 1ps $end

 $scope module TOP $end
  $var wire  1 & clk $end
  $var wire  9 ) delayed_signal [8:0] $end
  $var wire  9 ( mic_signal [8:0] $end
  $var wire  9 ' offset [8:0] $end
  $var wire  1 % rd $end
  $var wire  1 # rst $end
  $var wire  1 $ wr $end
  $scope module sigdelay $end
   $var wire  9 * addr1 [8:0] $end
   $var wire  1 & clk $end
   $var wire  9 ) delayed_signal [8:0] $end
   $var wire  9 ( mic_signal [8:0] $end
   $var wire  9 ' offset [8:0] $end
   $var wire  1 % rd $end
   $var wire  1 # rst $end
   $var wire  1 $ wr $end
   $scope module counter $end
    $var wire  1 & clk $end
    $var wire  9 * count [8:0] $end
    $var wire  1 $ en $end
    $var wire  9 ( incr [8:0] $end
    $var wire  1 # rst $end
   $upscope $end
   $scope module ram $end
    $var wire  1 & clk $end
    $var wire  9 ( din [8:0] $end
    $var wire  9 ) dout [8:0] $end
    $var wire  9 + rd_addr [8:0] $end
    $var wire  1 % rd_en $end
    $var wire  9 * wr_addr [8:0] $end
    $var wire  1 $ wr_en $end
   $upscope $end
  $upscope $end
 $upscope $end
$enddefinitions $end


#0
0#
1$
1%
1&
b001000000 '
b000000000 (
b000000000 )
b000000000 *
b001000000 +
#1
0&
#2
1&
b000000001 '
b001110010 (
b000000001 +
#3
0&
#4
1&
b001101100 (
b001110010 *
b001110011 +
#5
0&
#6
1&
b001101101 (
b011011110 *
b011011111 +
#7
0&
#8
1&
b001101111 (
b101001011 *
b101001100 +
#9
0&
#10
1&
b110111010 *
b110111011 +
#11
0&
#12
1&
b001101101 (
b000101001 *
b000101010 +
#13
0&
#14
1&
b001101110 (
b010010110 *
b010010111 +
#15
0&
#16
1&
b001101111 (
b100000100 *
b100000101 +
#17
0&
#18
1&
b001101110 (
b101110011 *
b101110100 +
#19
0&
#20
1&
b111100001 *
b111100010 +
#21
0&
#22
1&
b001001111 *
b001010000 +
#23
0&
#24
1&
b001101100 (
b010111101 *
b010111110 +
#25
0&
#26
1&
b001101110 (
b100101001 *
b100101010 +
#27
0&
#28
1&
b001101101 (
b110010111 *
b110011000 +
#29
0&
#30
1&
b000000100 *
b000000101 +
#31
0&
#32
1&
b001101111 (
b001110001 *
b001110010 +
#33
0&
#34
1&
b001101100 (
b001101100 )
b011100000 *
b011100001 +
#35
0&
#36
1&
b001101010 (
b000000000 )
b101001100 *
b101001101 +
#37
0&
#38
1&
b001101001 (
b110110110 *
b110110111 +
#39
0&
#40
1&
b001101011 (
b000011111 *
b000100000 +
#41
0&
#42
1&
b001101010 (
b010001010 *
b010001011 +
#43
0&
#44
1&
b001101110 (
b011110100 *
b011110101 +
#45
0&
#46
1&
b001101101 (
b101100010 *
b101100011 +
#47
0&
#48
1&
b001101011 (
b111001111 *
b111010000 +
#49
0&
#50
1&
b001101110 (
b000111010 *
b000111011 +
#51
0&
#52
1&
b001101101 (
b010101000 *
b010101001 +
#53
0&
#54
1&
b001101010 (
b100010101 *
b100010110 +
#55
0&
#56
1&
b001101100 (
b101111111 *
b110000000 +
#57
0&
#58
1&
b111101011 *
b111101100 +
#59
0&
#60
1&
b001010111 *
b001011000 +
#61
0&
#62
1&
b001101101 (
b011000011 *
b011000100 +
#63
0&
#64
1&
b100110000 *
b100110001 +
#65
0&
#66
1&
b001101011 (
b110011101 *
b110011110 +
#67
0&
#68
1&
b001101101 (
b000001000 *
b000001001 +
#69
0&
#70
1&
b001101011 (
b001110101 *
b001110110 +
#71
0&
#72
1&
b001101001 (
b011100000 *
b011100001 +
#73
0&
#74
1&
b001101100 (
b101001001 *
b101001010 +
#75
0&
#76
1&
b001101101 (
b110110101 *
b110110110 +
#77
0&
#78
1&
b001101100 (
b001101001 )
b000100010 *
b000100011 +
#79
0&
#80
1&
b001101101 (
b000000000 )
b010001110 *
b010001111 +
#81
0&
#82
1&
b001101110 (
b011111011 *
b011111100 +
#83
0&
#84
1&
b001101100 (
b101101001 *
b101101010 +
#85
0&
#86
1&
b001101110 (
b111010101 *
b111010110 +
#87
0&
#88
1&
b001101100 (
b001000011 *
b001000100 +
#89
0&
#90
1&
b001101101 (
b010101111 *
b010110000 +
#91
0&
#92
1&
b001101100 (
b100011100 *
b100011101 +
#93
0&
#94
1&
b001101010 (
b110001000 *
b110001001 +
#95
0&
#96
1&
b111110010 *
b111110011 +
#97
0&
#98
1&
b001101100 (
b001011100 *
b001011101 +
#99
0&
#100
1&
b001101010 (
b011001000 *
b011001001 +
#101
0&
#102
1&
b001101101 (
b100110010 *
b100110011 +
#103
0&
#104
1&
b001110000 (
b110011111 *
b110100000 +
#105
0&
#106
1&
b001101110 (
b000001111 *
b000010000 +
#107
0&
#108
1&
b001101011 (
b001111101 *
b001111110 +
#109
0&
#110
1&
b001101100 (
b011101000 *
b011101001 +
#111
0&
#112
1&
b001101011 (
b101010100 *
b101010101 +
#113
0&
#114
1&
b110111111 *
b111000000 +
#115
0&
#116
1&
b001101001 (
b000101010 *
b000101011 +
#117
0&
#118
1&
b001101000 (
b010010011 *
b010010100 +
#119
0&
#120
1&
b001101010 (
b011111011 *
b011111100 +
#121
0&
#122
1&
b101100101 *
b101100110 +
#123
0&
#124
1&
b111001111 *
b111010000 +
#125
0&
#126
1&
b001101100 (
b000111001 *
b000111010 +
#127
0&
#128
1&
b001101110 )
b010100101 *
b010100110 +
#129
0&
#130
1&
b001101000 (
b000000000 )
b100010001 *
b100010010 +
#131
0&
#132
1&
b001101101 (
b101111001 *
b101111010 +
#133
0&
#134
1&
b001101010 (
b111100110 *
b111100111 +
#135
0&
#136
1&
b001010000 *
b001010001 +
#137
0&
#138
1&
b001101101 (
b010111010 *
b010111011 +
#139
0&
#140
1&
b001101011 (
b100100111 *
b100101000 +
#141
0&
#142
1&
b001101010 (
b110010010 *
b110010011 +
#143
0&
#144
1&
b001100110 (
b111111100 *
b111111101 +
#145
0&
#146
1&
b001100111 (
b001100010 *
b001100011 +
#147
0&
#148
1&
b001100101 (
b011001001 *
b011001010 +
#149
0&
#150
1&
b001100110 (
b100101110 *
b100101111 +
#151
0&
#152
1&
b001100100 (
b110010100 *
b110010101 +
#153
0&
#154
1&
b001100111 (
b111111000 *
b111111001 +
#155
0&
#156
1&
b001101001 (
b001011111 *
b001100000 +
#157
0&
#158
1&
b001100110 (
b011001000 *
b011001001 +
#159
0&
#160
1&
b001100101 (
b001100101 )
b100101110 *
b100101111 +
#161
0&
#162
1&
b001100110 (
b000000000 )
b110010011 *
b110010100 +
#163
0&
#164
1&
b001101100 (
b001100100 )
b111111001 *
b111111010 +
#165
0&
#166
1&
b001101011 (
b000000000 )
b001100101 *
b001100110 +
#167
0&
#168
1&
b001101111 (
b011010000 *
b011010001 +
#169
0&
#170
1&
b001101010 (
b100111111 *
b101000000 +
#171
0&
#172
1&
b001100111 (
b110101001 *
b110101010 +
#173
0&
#174
1&
b001101001 (
b000010000 *
b000010001 +
#175
0&
#176
1&
b001100111 (
b001111001 *
b001111010 +
#177
0&
#178
1&
b011100000 *
b011100001 +
#179
0&
#180
1&
b001100110 (
b101000111 *
b101001000 +
#181
0&
#182
1&
b001100111 (
b110101101 *
b110101110 +
#183
0&
#184
1&
b001101001 (
b000010100 *
b000010101 +
#185
0&
#186
1&
b001101101 (
b001111101 *
b001111110 +
#187
0&
#188
1&
b001101011 (
b011101010 *
b011101011 +
#189
0&
#190
1&
b001101010 (
b101010101 *
b101010110 +
#191
0&
#192
1&
b110111111 *
b111000000 +
#193
0&
#194
1&
b001101011 (
b000101001 *
b000101010 +
#195
0&
#196
1&
b001101000 (
b001101001 )
b010010100 *
b010010101 +
#197
0&
#198
1&
b001101001 (
b000000000 )
b011111100 *
b011111101 +
#199
0&
#200
1&
b001101100 (
b101100101 *
b101100110 +
#201
0&
#202
1&
b001100111 (
b111010001 *
b111010010 +
#203
0&
#204
1&
b001101010 (
b000111000 *
b000111001 +
#205
0&
#206
1&
b001101011 (
b001101100 )
b010100010 *
b010100011 +
#207
0&
#208
1&
b001101110 (
b000000000 )
b100001101 *
b100001110 +
#209
0&
#210
1&
b001101001 (
b101111011 *
b101111100 +
#211
0&
#212
1&
b001101101 (
b111100100 *
b111100101 +
#213
0&
#214
1&
b001101001 (
b001010001 *
b001010010 +
#215
0&
#216
1&
b010111010 *
b010111011 +
#217
0&
#218
1&
b001100111 (
b100100011 *
b100100100 +
#219
0&
#220
1&
b001101001 (
b110001010 *
b110001011 +
#221
0&
#222
1&
b001100111 (
b111110011 *
b111110100 +
#223
0&
#224
1&
b001101001 (
b001011010 *
b001011011 +
#225
0&
#226
1&
b001100110 (
b011000011 *
b011000100 +
#227
0&
#228
1&
b001100111 (
b100101001 *
b100101010 +
#229
0&
#230
1&
b001101000 (
b110010000 *
b110010001 +
#231
0&
#232
1&
b001101001 (
b111111000 *
b111111001 +
#233
0&
#234
1&
b001100111 (
b001101100 )
b001100001 *
b001100010 +
#235
0&
#236
1&
b001101000 (
b001100111 )
b011001000 *
b011001001 +
#237
0&
#238
1&
b001101001 (
b001100101 )
b100110000 *
b100110001 +
#239
0&
#240
1&
b001101010 (
b000000000 )
b110011001 *
b110011010 +
#241
0&
#242
1&
b001101011 (
b000000011 *
b000000100 +
#243
0&
#244
1&
b001101101 )
b001101110 *
b001101111 +
#245
0&
#246
1&
b000000000 )
b011011001 *
b011011010 +
#247
0&
#248
1&
b001101101 (
b101000100 *
b101000101 +
#249
0&
#250
1&
b001101011 (
b110110001 *
b110110010 +
#251
0&
#252
1&
b001101010 (
b000011100 *
b000011101 +
#253
0&
#254
1&
b001101011 (
b010000110 *
b010000111 +
#255
0&
#256
1&
b001101010 (
b011110001 *
b011110010 +
#257
0&
#258
1&
b001101000 (
b101011011 *
b101011100 +
#259
0&
#260
1&
b001100110 (
b111000011 *
b111000100 +
#261
0&
#262
1&
b001100111 (
b000101001 *
b000101010 +
#263
0&
#264
1&
b001101100 (
b001101001 )
b010010000 *
b010010001 +
#265
0&
#266
1&
b001101011 (
b000000000 )
b011111100 *
b011111101 +
#267
0&
#268
1&
b001101110 (
b101100111 *
b101101000 +
#269
0&
#270
1&
b001101111 (
b111010101 *
b111010110 +
#271
0&
#272
1&
b001101100 (
b001000100 *
b001000101 +
#273
0&
#274
1&
b001101010 (
b010110000 *
b010110001 +
#275
0&
#276
1&
b001101101 (
b100011010 *
b100011011 +
#277
0&
#278
1&
b001101010 (
b110000111 *
b110001000 +
#279
0&
#280
1&
b001101011 (
b001101010 )
b111110001 *
b111110010 +
#281
0&
#282
1&
b001100111 (
b001011100 *
b001011101 +
#283
0&
#284
1&
b001101011 (
b000000000 )
b011000011 *
b011000100 +
#285
0&
#286
1&
b001101010 (
b100101110 *
b100101111 +
#287
0&
#288
1&
b001101101 (
b110011000 *
b110011001 +
#289
0&
#290
1&
b001101111 (
b001101010 )
b000000101 *
b000000110 +
#291
0&
#292
1&
b001101010 (
b000000000 )
b001110100 *
b001110101 +
#293
0&
#294
1&
b001101100 (
b001101011 )
b011011110 *
b011011111 +
#295
0&
#296
1&
b001110001 (
b000000000 )
b101001010 *
b101001011 +
#297
0&
#298
1&
b001101011 (
b001101111 )
b110111011 *
b110111100 +
#299
0&
#300
1&
b001100111 (
b000000000 )
b000100110 *
b000100111 +
#301
0&
#302
1&
b001101010 (
b010001101 *
b010001110 +
#303
0&
#304
1&
b001101001 (
b001101101 )
b011110111 *
b011111000 +
#305
0&
#306
1&
b000000000 )
b101100000 *
b101100001 +
#307
0&
#308
1&
b111001001 *
b111001010 +
#309
0&
#310
1&
b001101100 (
b000110010 *
b000110011 +
#311
0&
#312
1&
b001101010 (
b010011110 *
b010011111 +
#313
0&
#314
1&
b001101000 (
b100001000 *
b100001001 +
#315
0&
#316
1&
b101110000 *
b101110001 +
#317
0&
#318
1&
b001101001 (
b111011000 *
b111011001 +
#319
0&
#320
1&
b001101010 (
b001000001 *
b001000010 +
#321
0&
#322
1&
b001101000 (
b010101011 *
b010101100 +
#323
0&
#324
1&
b001101011 (
b100010011 *
b100010100 +
#325
0&
#326
1&
b001101110 (
b101111110 *
b101111111 +
#327
0&
#328
1&
b001101010 (
b001101100 )
b111101100 *
b111101101 +
#329
0&
#330
1&
b001101101 (
b000000000 )
b001010110 *
b001010111 +
#331
0&
#332
1&
b001101111 (
b001101100 )
b011000011 *
b011000100 +
#333
0&
#334
1&
b001101011 (
b000000000 )
b100110010 *
b100110011 +
#335
0&
#336
1&
b001101001 (
b110011101 *
b110011110 +
#337
0&
#338
1&
b001101011 (
b000000110 *
b000000111 +
#339
0&
#340
1&
b001100110 (
b001110001 *
b001110010 +
#341
0&
#342
1&
b001100111 (
b001101100 )
b011010111 *
b011011000 +
#343
0&
#344
1&
b001100110 (
b000000000 )
b100111110 *
b100111111 +
#345
0&
#346
1&
b001101000 (
b001101010 )
b110100100 *
b110100101 +
#347
0&
#348
1&
b001101010 (
b000000000 )
b000001100 *
b000001101 +
#349
0&
#350
1&
b001101000 (
b001110110 *
b001110111 +
#351
0&
#352
1&
b001101010 (
b011011110 *
b011011111 +
#353
0&
#354
1&
b001101101 (
b101001000 *
b101001001 +
#355
0&
#356
1&
b001101010 (
b001101100 )
b110110101 *
b110110110 +
#357
0&
#358
1&
b001101100 (
b001101001 )
b000011111 *
b000100000 +
#359
0&
#360
1&
b001101011 (
b000000000 )
b010001011 *
b010001100 +
#361
0&
#362
1&
b001101101 (
b011110110 *
b011110111 +
#363
0&
#364
1&
b001101011 (
b001101001 )
b101100011 *
b101100100 +
#365
0&
#366
1&
b001101000 (
b000000000 )
b111001110 *
b111001111 +
#367
0&
#368
1&
b001100110 (
b001101010 )
b000110110 *
b000110111 +
#369
0&
#370
1&
b001100111 (
b000000000 )
b010011100 *
b010011101 +
#371
0&
#372
1&
b001101000 (
b100000011 *
b100000100 +
#373
0&
#374
1&
b001101011 (
b001101111 )
b101101011 *
b101101100 +
#375
0&
#376
1&
b001101010 (
b000000000 )
b111010110 *
b111010111 +
#377
0&
#378
1&
b001000000 *
b001000001 +
#379
0&
#380
1&
b001100111 (
b001101010 )
b010101010 *
b010101011 +
#381
0&
#382
1&
b001101001 (
b001101000 )
b100010001 *
b100010010 +
#383
0&
#384
1&
b001100111 (
b000000000 )
b101111010 *
b101111011 +
#385
0&
#386
1&
b001101010 (
b001101001 )
b111100001 *
b111100010 +
#387
0&
#388
1&
b001100101 (
b000000000 )
b001001011 *
b001001100 +
#389
0&
#390
1&
b001100111 (
b010110000 *
b010110001 +
#391
0&
#392
1&
b001100100 (
b100010111 *
b100011000 +
#393
0&
#394
1&
b001101001 (
b101111011 *
b101111100 +
#395
0&
#396
1&
b001101000 (
b111100100 *
b111100101 +
#397
0&
#398
1&
b001100111 (
b001001100 *
b001001101 +
#399
0&
#400
1&
b001101010 (
b010110011 *
b010110100 +
#401
0&
#402
1&
b001101110 (
b100011101 *
b100011110 +
#403
0&
#404
1&
b001101101 (
b110001011 *
b110001100 +
#405
0&
#406
1&
b001101010 (
b111111000 *
b111111001 +
#407
0&
#408
1&
b001101001 (
b001101100 )
b001100010 *
b001100011 +
#409
0&
#410
1&
b000000000 )
b011001011 *
b011001100 +
#411
0&
#412
1&
b100110100 *
b100110101 +
#413
0&
#414
1&
b001101000 (
b110011101 *
b110011110 +
#415
0&
#416
1&
b000000101 *
b000000110 +
#417
0&
#418
1&
b001101011 )
b001101101 *
b001101110 +
#419
0&
#420
1&
b011010101 *
b011010110 +
#421
0&
#422
1&
b001101001 (
b000000000 )
b100111101 *
b100111110 +
#423
0&
#424
1&
b001100111 (
b001100110 )
b110100110 *
b110100111 +
#425
0&
#426
1&
b000000000 )
b000001101 *
b000001110 +
#427
0&
#428
1&
b001101010 (
b001110100 *
b001110101 +
#429
0&
#430
1&
b001101100 (
b001101011 )
b011011110 *
b011011111 +
#431
0&
#432
1&
b001101001 (
b000000000 )
b101001010 *
b101001011 +
#433
0&
#434
1&
b001101111 )
b110110011 *
b110110100 +
#435
0&
#436
1&
b001101101 (
b000000000 )
b000011100 *
b000011101 +
#437
0&
#438
1&
b001101001 (
b010001001 *
b010001010 +
#439
0&
#440
1&
b001101010 )
b011110010 *
b011110011 +
#441
0&
#442
1&
b001101100 (
b000000000 )
b101011011 *
b101011100 +
#443
0&
#444
1&
b001101000 (
b111000111 *
b111001000 +
#445
0&
#446
1&
b001100111 (
b000101111 *
b000110000 +
#447
0&
#448
1&
b010010110 *
b010010111 +
#449
0&
#450
1&
b001101001 (
b011111101 *
b011111110 +
#451
0&
#452
1&
b001101000 (
b101100110 *
b101100111 +
#453
0&
#454
1&
b001101110 )
b111001110 *
b111001111 +
#455
0&
#456
1&
b001100111 (
b001101010 )
b000110110 *
b000110111 +
#457
0&
#458
1&
b001100100 (
b000000000 )
b010011101 *
b010011110 +
#459
0&
#460
1&
b001101010 (
b001101010 )
b100000001 *
b100000010 +
#461
0&
#462
1&
b001101000 (
b000000000 )
b101101011 *
b101101100 +
#463
0&
#464
1&
b001101001 (
b111010011 *
b111010100 +
#465
0&
#466
1&
b000111100 *
b000111101 +
#467
0&
#468
1&
b001101000 (
b010100101 *
b010100110 +
#469
0&
#470
1&
b001100111 (
b100001101 *
b100001110 +
#471
0&
#472
1&
b001101011 (
b101110100 *
b101110101 +
#473
0&
#474
1&
b001101110 (
b111011111 *
b111100000 +
#475
0&
#476
1&
b001101100 (
b001001101 *
b001001110 +
#477
0&
#478
1&
b001101011 (
b010111001 *
b010111010 +
#479
0&
#480
1&
b001101001 (
b001101001 )
b100100100 *
b100100101 +
#481
0&
#482
1&
b001101010 (
b000000000 )
b110001101 *
b110001110 +
#483
0&
#484
1&
b111110111 *
b111111000 +
#485
0&
#486
1&
b001101001 (
b001101010 )
b001100001 *
b001100010 +
#487
0&
#488
1&
b001100111 (
b001101001 )
b011001010 *
b011001011 +
#489
0&
#490
1&
b100110001 *
b100110010 +
#491
0&
#492
1&
b001101011 )
b110011000 *
b110011001 +
#493
0&
#494
1&
b001101001 (
b001101010 )
b111111111 *
b000000000 +
#495
0&
#496
1&
b001101000 (
b001110010 )
b001101000 *
b001101001 +
#497
0&
#498
1&
b001101001 (
b000000000 )
b011010000 *
b011010001 +
#499
0&
#500
1&
b001101010 (
b100111001 *
b100111010 +
#501
0&
#502
1&
b001101011 (
b110100011 *
b110100100 +
#503
0&
#504
1&
b001101001 (
b001101000 )
b000001110 *
b000001111 +
#505
0&
#506
1&
b001101110 )
b001110111 *
b001111000 +
#507
0&
#508
1&
b001101010 (
b000000000 )
b011100000 *
b011100001 +
#509
0&
#510
1&
b001101001 (
b101001010 *
b101001011 +
#511
0&
#512
1&
b001101011 (
b001101111 )
b110110011 *
b110110100 +
#513
0&
#514
1&
b001101100 (
b000000000 )
b000011110 *
b000011111 +
#515
0&
#516
1&
b001101010 (
b001101100 )
b010001010 *
b010001011 +
#517
0&
#518
1&
b001101001 (
b001101011 )
b011110100 *
b011110101 +
#519
0&
#520
1&
b001101010 (
b000000000 )
b101011101 *
b101011110 +
#521
0&
#522
1&
b001101001 (
b111000111 *
b111001000 +
#523
0&
#524
1&
b001101100 (
b000110000 *
b000110001 +
#525
0&
#526
1&
b001100111 (
b010011100 *
b010011101 +
#527
0&
#528
1&
b001101000 (
b001100100 )
b100000011 *
b100000100 +
#529
0&
#530
1&
b001101111 )
b101101011 *
b101101100 +
#531
0&
#532
1&
b001101010 (
b000000000 )
b111010011 *
b111010100 +
#533
0&
#534
1&
b000111101 *
b000111110 +
#535
0&
#536
1&
b001100111 (
b010100111 *
b010101000 +
#537
0&
#538
1&
b001101101 )
b100001110 *
b100001111 +
#539
0&
#540
1&
b001101001 (
b000000000 )
b101110101 *
b101110110 +
#541
0&
#542
1&
b111011110 *
b111011111 +
#543
0&
#544
1&
b001101110 )
b001000111 *
b001001000 +
#545
0&
#546
1&
b001101010 (
b000000000 )
b010110000 *
b010110001 +
#547
0&
#548
1&
b001101101 (
b100011010 *
b100011011 +
#549
0&
#550
1&
b001101000 (
b110000111 *
b110001000 +
#551
0&
#552
1&
b001100111 (
b001101010 )
b111101111 *
b111110000 +
#553
0&
#554
1&
b001101000 (
b000000000 )
b001010110 *
b001010111 +
#555
0&
#556
1&
b001100111 (
b001101100 )
b010111110 *
b010111111 +
#557
0&
#558
1&
b001101011 (
b000000000 )
b100100101 *
b100100110 +
#559
0&
#560
1&
b001101000 (
b110010000 *
b110010001 +
#561
0&
#562
1&
b001101001 (
b111111000 *
b111111001 +
#563
0&
#564
1&
b001100110 (
b001101100 )
b001100001 *
b001100010 +
#565
0&
#566
1&
b001100111 (
b001101001 )
b011000111 *
b011001000 +
#567
0&
#568
1&
b001100101 (
b001101000 )
b100101110 *
b100101111 +
#569
0&
#570
1&
b001101000 (
b000000000 )
b110010011 *
b110010100 +
#571
0&
#572
1&
b001101001 (
b001100100 )
b111111011 *
b111111100 +
#573
0&
#574
1&
b001100111 (
b001100110 )
b001100100 *
b001100101 +
#575
0&
#576
1&
b001101010 (
b001101011 )
b011001011 *
b011001100 +
#577
0&
#578
1&
b001100101 (
b000000000 )
b100110101 *
b100110110 +
#579
0&
#580
1&
b001101011 (
b110011010 *
b110011011 +
#581
0&
#582
1&
b001101001 (
b000000101 *
b000000110 +
#583
0&
#584
1&
b001101011 )
b001101110 *
b001101111 +
#585
0&
#586
1&
b001101010 (
b000000000 )
b011010111 *
b011011000 +
#587
0&
#588
1&
b001101000 (
b101000001 *
b101000010 +
#589
0&
#590
1&
b001101110 (
b110101001 *
b110101010 +
#591
0&
#592
1&
b001101101 (
b000010111 *
b000011000 +
#593
0&
#594
1&
b001101011 (
b010000100 *
b010000101 +
#595
0&
#596
1&
b001101101 (
b011101111 *
b011110000 +
#597
0&
#598
1&
b001101011 (
b101011100 *
b101011101 +
#599
0&
#600
1&
b001100110 (
b001101010 )
b111000111 *
b111001000 +
#601
0&
#602
1&
b001101010 (
b000000000 )
b000101101 *
b000101110 +
#603
0&
#604
1&
b001101001 (
b010010111 *
b010011000 +
#605
0&
#606
1&
b001100110 (
b100000000 *
b100000001 +
#607
0&
#608
1&
b001101010 )
b101100110 *
b101100111 +
#609
0&
#610
1&
b001101011 (
b001101110 )
b111001100 *
b111001101 +
#611
0&
#612
1&
b000000000 )
b000110111 *
b000111000 +
#613
0&
#614
1&
b001101001 (
b001101010 )
b010100010 *
b010100011 +
#615
0&
#616
1&
b001101010 (
b000000000 )
b100001011 *
b100001100 +
#617
0&
#618
1&
b101110101 *
b101110110 +
#619
0&
#620
1&
b111011111 *
b111100000 +
#621
0&
#622
1&
b001101001 (
b001001001 *
b001001010 +
#623
0&
#624
1&
b001101010 (
b010110010 *
b010110011 +
#625
0&
#626
1&
b001101001 (
b001101010 )
b100011100 *
b100011101 +
#627
0&
#628
1&
b001101000 (
b001101110 )
b110000101 *
b110000110 +
#629
0&
#630
1&
b001101001 (
b000000000 )
b111101101 *
b111101110 +
#631
0&
#632
1&
b001101000 (
b001010110 *
b001010111 +
#633
0&
#634
1&
b001101011 (
b001101100 )
b010111110 *
b010111111 +
#635
0&
#636
1&
b000000000 )
b100101001 *
b100101010 +
#637
0&
#638
1&
b001101000 (
b110010100 *
b110010101 +
#639
0&
#640
1&
b001101001 (
b111111100 *
b111111101 +
#641
0&
#642
1&
b001101011 (
b001100101 *
b001100110 +
#643
0&
#644
1&
b001101010 (
b011010000 *
b011010001 +
#645
0&
#646
1&
b001101001 (
b100111010 *
b100111011 +
#647
0&
#648
1&
b001101010 (
b110100011 *
b110100100 +
#649
0&
#650
1&
b001100111 (
b001101000 )
b000001101 *
b000001110 +
#651
0&
#652
1&
b001100110 (
b001101001 )
b001110100 *
b001110101 +
#653
0&
#654
1&
b001100111 (
b001101011 )
b011011010 *
b011011011 +
#655
0&
#656
1&
b001101001 (
b000000000 )
b101000001 *
b101000010 +
#657
0&
#658
1&
b001101011 (
b110101010 *
b110101011 +
#659
0&
#660
1&
b000010101 *
b000010110 +
#661
0&
#662
1&
b010000000 *
b010000001 +
#663
0&
#664
1&
b001101010 (
b011101011 *
b011101100 +
#665
0&
#666
1&
b001101001 (
b101010101 *
b101010110 +
#667
0&
#668
1&
b001101010 (
b110111110 *
b110111111 +
#669
0&
#670
1&
b001101001 (
b001101010 )
b000101000 *
b000101001 +
#671
0&
#672
1&
b001101010 (
b001100111 )
b010010001 *
b010010010 +
#673
0&
#674
1&
b001101000 (
b000000000 )
b011111011 *
b011111100 +
#675
0&
#676
1&
b001101001 (
b001101011 )
b101100011 *
b101100100 +
#677
0&
#678
1&
b001101000 (
b000000000 )
b111001100 *
b111001101 +
#679
0&
#680
1&
b001101001 (
b000110100 *
b000110101 +
#681
0&
#682
1&
b001101100 (
b010011101 *
b010011110 +
#683
0&
#684
1&
b001101010 (
b001101010 )
b100001001 *
b100001010 +
#685
0&
#686
1&
b001101011 (
b000000000 )
b101110011 *
b101110100 +
#687
0&
#688
1&
b001101001 (
b001101011 )
b111011110 *
b111011111 +
#689
0&
#690
1&
b001101011 (
b001101010 )
b001000111 *
b001001000 +
#691
0&
#692
1&
b000000000 )
b010110010 *
b010110011 +
#693
0&
#694
1&
b001100111 (
b001101010 )
b100011101 *
b100011110 +
#695
0&
#696
1&
b001100110 (
b000000000 )
b110000100 *
b110000101 +
#697
0&
#698
1&
b001100111 (
b001101000 )
b111101010 *
b111101011 +
#699
0&
#700
1&
b001101100 )
b001010001 *
b001010010 +
#701
0&
#702
1&
b001101011 (
b000000000 )
b010111000 *
b010111001 +
#703
0&
#704
1&
b001100101 (
b001101011 )
b100100011 *
b100100100 +
#705
0&
#706
1&
b001101001 (
b001101001 )
b110001000 *
b110001001 +
#707
0&
#708
1&
b001101000 (
b000000000 )
b111110001 *
b111110010 +
#709
0&
#710
1&
b001101010 (
b001101010 )
b001011001 *
b001011010 +
#711
0&
#712
1&
b001101001 (
b001101001 )
b011000011 *
b011000100 +
#713
0&
#714
1&
b001101000 (
b000000000 )
b100101100 *
b100101101 +
#715
0&
#716
1&
b001101100 (
b110010100 *
b110010101 +
#717
0&
#718
1&
b001101011 (
b000000000 *
b000000001 +
#719
0&
#720
1&
b001101010 (
b001101011 *
b001101100 +
#721
0&
#722
1&
b001101011 (
b011010101 *
b011010110 +
#723
0&
#724
1&
b001101001 (
b101000000 *
b101000001 +
#725
0&
#726
1&
b001100111 (
b001101001 )
b110101001 *
b110101010 +
#727
0&
#728
1&
b001101001 (
b001101011 )
b000010000 *
b000010001 +
#729
0&
#730
1&
b000000000 )
b001111001 *
b001111010 +
#731
0&
#732
1&
b011100010 *
b011100011 +
#733
0&
#734
1&
b001101011 (
b101001011 *
b101001100 +
#735
0&
#736
1&
b001101100 (
b001101010 )
b110110110 *
b110110111 +
#737
0&
#738
1&
b001101011 (
b000000000 )
b000100010 *
b000100011 +
#739
0&
#740
1&
b001101001 (
b010001101 *
b010001110 +
#741
0&
#742
1&
b001101011 (
b001101101 )
b011110110 *
b011110111 +
#743
0&
#744
1&
b001101100 (
b001101001 )
b101100001 *
b101100010 +
#745
0&
#746
1&
b001100111 (
b001101101 )
b111001101 *
b111001110 +
#747
0&
#748
1&
b001101011 (
b001101000 )
b000110100 *
b000110101 +
#749
0&
#750
1&
b001100111 (
b000000000 )
b010011111 *
b010100000 +
#751
0&
#752
1&
b001101100 (
b100000110 *
b100000111 +
#753
0&
#754
1&
b001101000 (
b101110010 *
b101110011 +
#755
0&
#756
1&
b001101011 )
b111011010 *
b111011011 +
#757
0&
#758
1&
b001101001 (
b000000000 )
b001000010 *
b001000011 +
#759
0&
#760
1&
b001101100 )
b010101011 *
b010101100 +
#761
0&
#762
1&
b001100111 (
b000000000 )
b100010100 *
b100010101 +
#763
0&
#764
1&
b001100110 (
b001101010 )
b101111011 *
b101111100 +
#765
0&
#766
1&
b001101010 (
b000000000 )
b111100001 *
b111100010 +
#767
0&
#768
1&
b001101001 (
b001001011 *
b001001100 +
#769
0&
#770
1&
b001100111 (
b001100111 )
b010110100 *
b010110101 +
#771
0&
#772
1&
b001101010 (
b000000000 )
b100011011 *
b100011100 +
#773
0&
#774
1&
b001101101 (
b001101001 )
b110000101 *
b110000110 +
#775
0&
#776
1&
b001101011 (
b000000000 )
b111110010 *
b111110011 +
#777
0&
#778
1&
b001100111 (
b001100111 )
b001011101 *
b001011110 +
#779
0&
#780
1&
b001101011 (
b000000000 )
b011000100 *
b011000101 +
#781
0&
#782
1&
b001100111 (
b100101111 *
b100110000 +
#783
0&
